pdfToJson/__init__.py
pdfToJson/client.py
pdfToJson/pdfClient.py
pdfToJson/xmlToJson.py
pdfToJson-0.0.2.dist-info/LICENSE
pdfToJson-0.0.2.dist-info/METADATA
pdfToJson-0.0.2.dist-info/WHEEL
pdfToJson-0.0.2.dist-info/top_level.txt
pdfToJson-0.0.2.dist-info/RECORD
