Metadata-Version: 2.1
Name: pdfToJson
Version: 0.0.2
Summary: This is a package which converts pdf to json using GROBID
Home-page: UNKNOWN
Author: xjw
Author-email: XiongJingWen_0629@163.com
License: UNKNOWN
Platform: UNKNOWN
